trytond/modules/cashbook/README.rst
trytond/modules/cashbook/__init__.py
trytond/modules/cashbook/book.py
trytond/modules/cashbook/book.xml
trytond/modules/cashbook/category.py
trytond/modules/cashbook/category.xml
trytond/modules/cashbook/cbreport.py
trytond/modules/cashbook/cbreport.xml
trytond/modules/cashbook/configuration.py
trytond/modules/cashbook/configuration.xml
trytond/modules/cashbook/const.py
trytond/modules/cashbook/cron.py
trytond/modules/cashbook/cron.xml
trytond/modules/cashbook/currency.py
trytond/modules/cashbook/group.xml
trytond/modules/cashbook/icon.xml
trytond/modules/cashbook/ir.py
trytond/modules/cashbook/line.py
trytond/modules/cashbook/line.xml
trytond/modules/cashbook/menu.xml
trytond/modules/cashbook/message.xml
trytond/modules/cashbook/mixin.py
trytond/modules/cashbook/model.py
trytond/modules/cashbook/reconciliation.py
trytond/modules/cashbook/reconciliation.xml
trytond/modules/cashbook/splitline.py
trytond/modules/cashbook/splitline.xml
trytond/modules/cashbook/tryton.cfg
trytond/modules/cashbook/types.py
trytond/modules/cashbook/types.xml
trytond/modules/cashbook/valuestore.py
trytond/modules/cashbook/versiondep.txt
trytond/modules/cashbook/wizard_booking.py
trytond/modules/cashbook/wizard_booking.xml
trytond/modules/cashbook/wizard_openline.py
trytond/modules/cashbook/wizard_openline.xml
trytond/modules/cashbook/wizard_runreport.py
trytond/modules/cashbook/wizard_runreport.xml
trytond/modules/cashbook/docs/settings.txt
trytond/modules/cashbook/icon/notebook1.svg
trytond/modules/cashbook/locale/de.po
trytond/modules/cashbook/locale/en.po
trytond/modules/cashbook/report/cashbook.fods
trytond/modules/cashbook/report/reconciliation.fods
trytond/modules/cashbook/tests/__init__.py
trytond/modules/cashbook/tests/book.py
trytond/modules/cashbook/tests/bookingwiz.py
trytond/modules/cashbook/tests/category.py
trytond/modules/cashbook/tests/config.py
trytond/modules/cashbook/tests/line.py
trytond/modules/cashbook/tests/reconciliation.py
mds_cashbook-7.0.41.dist-info/LICENSE
mds_cashbook-7.0.41.dist-info/METADATA
mds_cashbook-7.0.41.dist-info/WHEEL
mds_cashbook-7.0.41.dist-info/entry_points.txt
mds_cashbook-7.0.41.dist-info/top_level.txt
mds_cashbook-7.0.41.dist-info/RECORD
