Metadata-Version: 2.1
Name: mds-cashbook
Version: 7.0.41
Summary: Tryton module to add a cashbook.
Home-page: https://www.m-ds.de/
Author: martin-data services
Author-email: service@m-ds.de
License: GPL-3
Download-URL: https://scmforg.m-ds.de/mdsfred/cashbook
Keywords: tryton cashbook
Platform: UNKNOWN
Classifier: Development Status :: 5 - Production/Stable
Classifier: Environment :: Plugins
Classifier: Framework :: Tryton
Classifier: Intended Audience :: Developers
Classifier: Intended Audience :: Customer Service
Classifier: Intended Audience :: Information Technology
Classifier: Intended Audience :: Financial and Insurance Industry
Classifier: Topic :: Office/Business
Classifier: Topic :: Office/Business :: Financial :: Accounting
Classifier: Natural Language :: German
Classifier: Natural Language :: English
Classifier: Operating System :: OS Independent
Classifier: License :: OSI Approved :: GNU General Public License (GPL)
Classifier: Programming Language :: Python :: 3.7
Classifier: Programming Language :: Python :: 3.8
Classifier: Programming Language :: Python :: 3.9
Classifier: Programming Language :: Python :: 3.10
Classifier: Programming Language :: Python :: 3.11
Classifier: Programming Language :: Python :: 3.12
License-File: LICENSE
Requires-Dist: mds-irrulecontext (<=7.0.999,>=7.0.1)
Requires-Dist: python-slugify
Requires-Dist: trytond (<7.1,>=7.0)
Requires-Dist: trytond-company (<7.1,>=7.0)
Requires-Dist: trytond-currency (<7.1,>=7.0)
Requires-Dist: trytond-party (<7.1,>=7.0)
